qywx_app_message/__init__.py
qywx_app_message/qywx_app_message.py
qywx_app_message-2.0.7.dist-info/LICENSE
qywx_app_message-2.0.7.dist-info/METADATA
qywx_app_message-2.0.7.dist-info/WHEEL
qywx_app_message-2.0.7.dist-info/top_level.txt
qywx_app_message-2.0.7.dist-info/RECORD
